.QualityGate
.gitignore
.pylintrc
.python-version
.readthedocs.yaml
LICENSE
README.rst
SCR-fc.txt
requirements.txt
setup.cfg
setup.py
.github/workflows/main.yml
ci/black.sh
ci/docker.sh
ci/package.sh
ci/publish_docker.sh
ci/pylint.sh
ci/pytest.sh
ci/setup.sh
doc/Makefile
doc/conf.py
doc/configuration.rst
doc/index.rst
doc/make.bat
doc/overview.rst
doc/quickstart.rst
doc/support.rst
doc/usage.rst
doc/css/css-style.css
doc/images/architecture.svg
doc/images/era.svg
doc/images/fc.png
doc/images/flowchart.svg
doc/images/principle.svg
docker/fc_client/Dockerfile
docker/fc_client/fc-agent
docker/fc_client/fc-client
docker/fc_guarder/Dockerfile
docker/fc_guarder/docker-compose.yaml
docker/fc_guarder/entrypoint.sh
docker/fc_guarder/sample.env
docker/fc_server/Dockerfile
docker/fc_server/docker-compose.yaml
docker/fc_server/entrypoint.sh
fc_agent/agent.py
fc_client/client.py
fc_client/sample_client.env
fc_client_daemon/client_daemon.py
fc_client_docker/__init__.py
fc_client_docker/fc_client_docker
fc_common/VERSION
fc_common/__init__.py
fc_common/config.py
fc_common/etcd.py
fc_common/logger.py
fc_common/version.py
fc_guarder/guarder.py
fc_mcp/__init__.py
fc_mcp/mcp_base.py
fc_mcp/mcp_server.py
fc_mcp/mcp_plugins/__init__.py
fc_mcp/mcp_plugins/external/uboot_mcp.py
fc_mcp/mcp_plugins/external/uuu_bcu_mcp.py
fc_mcp/mcp_plugins/internal/__init__.py
fc_mcp/mcp_plugins/internal/fc_mcp.py
fc_server/__init__.py
fc_server/server.py
fc_server.egg-info/PKG-INFO
fc_server.egg-info/SOURCES.txt
fc_server.egg-info/dependency_links.txt
fc_server.egg-info/entry_points.txt
fc_server.egg-info/requires.txt
fc_server.egg-info/top_level.txt
fc_server/config/sample_cfg.yaml
fc_server/config/sample_lavacli.yaml
fc_server/config/sample_resource.yaml
fc_server/core/__init__.py
fc_server/core/api_svr.py
fc_server/core/config.py
fc_server/core/coordinator.py
fc_server/core/decorators.py
fc_server/core/plugin.py
fc_server/management/__init__.py
fc_server/management/cmd_online_lava_devices.py
fc_server/management/common.py
fc_server/plugins/__init__.py
fc_server/plugins/labgrid.py
fc_server/plugins/lava.py
fc_server/plugins/utils/__init__.py
fc_server/plugins/utils/labgrid.py
