Metadata-Version: 2.1
Name: fc_server
Version: 0.8.8
Home-page: https://fc.readthedocs.io/
Author: Larry Shen
Author-email: larry.shen@nxp.com
License: MIT
Classifier: Development Status :: 4 - Beta
Classifier: Environment :: Console
Classifier: Intended Audience :: Developers
Classifier: License :: OSI Approved :: MIT License
Classifier: Operating System :: POSIX :: Linux
Classifier: Programming Language :: Python
Classifier: Programming Language :: Python :: 3.8
Classifier: Programming Language :: Python :: 3.9
Classifier: Programming Language :: Python :: 3 :: Only
Requires-Python: >=3.8
License-File: LICENSE
Requires-Dist: aiohttp>=3.7.4.post0
Requires-Dist: async-lru>=1.0.3
Requires-Dist: flatdict>=4.0.1
Requires-Dist: lavacli==1.2
Requires-Dist: labgrid==23.1a2
Requires-Dist: singledispatchmethod>=1.0
Requires-Dist: python-prctl
Requires-Dist: etcd3-fc
Requires-Dist: tenacity
Requires-Dist: protobuf==3.20.3
Requires-Dist: prettytable>=2.2.1
